conan-stubs/__init__.pyi
conan-stubs/errors.pyi
conan-stubs/tools/__init__.pyi
conan-stubs/tools/_check_build_profile.pyi
conan-stubs/tools/_compilers.pyi
conan-stubs/tools/android/__init__.pyi
conan-stubs/tools/android/utils.pyi
conan-stubs/tools/apple/__init__.pyi
conan-stubs/tools/apple/apple.pyi
conan-stubs/tools/apple/xcodebuild.pyi
conan-stubs/tools/apple/xcodedeps.pyi
conan-stubs/tools/apple/xcodetoolchain.pyi
conan-stubs/tools/build/__init__.pyi
conan-stubs/tools/build/cppstd.pyi
conan-stubs/tools/build/cpu.pyi
conan-stubs/tools/build/cross_building.pyi
conan-stubs/tools/build/stdcpp_library.pyi
conan-stubs/tools/cmake/__init__.pyi
conan-stubs/tools/cmake/cmake.pyi
conan-stubs/tools/cmake/file_api.pyi
conan-stubs/tools/cmake/layout.pyi
conan-stubs/tools/cmake/presets.pyi
conan-stubs/tools/cmake/utils.pyi
conan-stubs/tools/cmake/cmakedeps/__init__.pyi
conan-stubs/tools/cmake/cmakedeps/cmakedeps.pyi
conan-stubs/tools/cmake/cmakedeps/templates/__init__.pyi
conan-stubs/tools/cmake/cmakedeps/templates/config.pyi
conan-stubs/tools/cmake/cmakedeps/templates/config_version.pyi
conan-stubs/tools/cmake/cmakedeps/templates/macros.pyi
conan-stubs/tools/cmake/cmakedeps/templates/target_configuration.pyi
conan-stubs/tools/cmake/cmakedeps/templates/target_data.pyi
conan-stubs/tools/cmake/cmakedeps/templates/targets.pyi
conan-stubs/tools/cmake/toolchain/__init__.pyi
conan-stubs/tools/cmake/toolchain/blocks.pyi
conan-stubs/tools/cmake/toolchain/toolchain.pyi
conan-stubs/tools/env/__init__.pyi
conan-stubs/tools/env/environment.pyi
conan-stubs/tools/env/virtualbuildenv.pyi
conan-stubs/tools/env/virtualrunenv.pyi
conan-stubs/tools/files/__init__.pyi
conan-stubs/tools/files/conandata.pyi
conan-stubs/tools/files/copy_pattern.pyi
conan-stubs/tools/files/cpp_package.pyi
conan-stubs/tools/files/files.pyi
conan-stubs/tools/files/packager.pyi
conan-stubs/tools/files/patches.pyi
conan-stubs/tools/files/symlinks/__init__.pyi
conan-stubs/tools/files/symlinks/symlinks.pyi
conan_stubs-1.59.0a4.dist-info/LICENSE
conan_stubs-1.59.0a4.dist-info/METADATA
conan_stubs-1.59.0a4.dist-info/WHEEL
conan_stubs-1.59.0a4.dist-info/top_level.txt
conan_stubs-1.59.0a4.dist-info/RECORD
