Metadata-Version: 2.1
Name: conan-stubs
Version: 1.59.0a4
Summary: Conan type stubs
Author: Peter Gosztolya
License: MIT License
Keywords: conan,stubs
Classifier: Programming Language :: Python :: 3
Classifier: Programming Language :: Python :: 3.8
Classifier: Programming Language :: Python :: 3.9
Classifier: Programming Language :: Python :: 3.10
Classifier: Programming Language :: Python :: 3.11
Requires-Python: >=3.8
License-File: LICENSE
